README.rst
setup.py
teacup.py
teacup.egg-info/PKG-INFO
teacup.egg-info/SOURCES.txt
teacup.egg-info/dependency_links.txt
teacup.egg-info/requires.txt
teacup.egg-info/top_level.txt
teacup.egg-info/zip-safe