Metadata-Version: 1.0
Name: teacup
Version: 0.9
Summary: HTML Templating DSL for Python
Home-page: https://github.com/benwbooth/python-teacup
Author: Ben Booth
Author-email: benwbooth@gmail.com
License: MIT
Keywords: python module html markdown teacup coffeecup coffeekup templating template library
Platform: UNKNOWN
